{"3": 0, "5": 1, "6": 2, "7": 3, "A4": 4, "A6": 5, "A8": 6, "Alto": 7, "Altroz": 8, "Alturas": 9, "Amaze": 10, "Aspire": 11, "Aura": 12, "Baleno": 13, "Bolero": 14, "C": 15, "C-Class": 16, "CLS": 17, "CR": 18, "CR-V": 19, "Camry": 20, "Carnival": 21, "Cayenne": 22, "Celerio": 23, "Ciaz": 24, "City": 25, "Civic": 26, "Compass": 27, "Continental": 28, "Cooper": 29, "Creta": 30, "D-Max": 31, "Duster": 32, "Dzire LXI": 33, "Dzire VXI": 34, "Dzire ZXI": 35, "E-Class": 36, "ES": 37, "Ecosport": 38, "Eeco": 39, "Elantra": 40, "Endeavour": 41, "Ertiga": 42, "F-PACE": 43, "Figo": 44, "Fortuner": 45, "Freestyle": 46, "GL-Class": 47, "GLS": 48, "GO": 49, "GTC4Lusso": 50, "Ghibli": 51, "Ghost": 52, "Glanza": 53, "Grand": 54, "Gurkha": 55, "Harrier": 56, "Hector": 57, "Hexa": 58, "Ignis": 59, "Innova": 60, "Jazz": 61, "KUV": 62, "KUV100": 63, "KWID": 64, "Kicks": 65, "MUX": 66, "Macan": 67, "Marazzo": 68, "NX": 69, "Nexon": 70, "Octavia": 71, "Panamera": 72, "Polo": 73, "Q7": 74, "Quattroporte": 75, "RX": 76, "Rapid": 77, "RediGO": 78, "Rover": 79, "S-Class": 80, "S-Presso": 81, "S90": 82, "Safari": 83, "Santro": 84, "Scorpio": 85, "Seltos": 86, "Superb": 87, "Swift": 88, "Swift Dzire": 89, "Thar": 90, "Tiago": 91, "Tigor": 92, "Triber": 93, "Tucson": 94, "Vento": 95, "Venue": 96, "Verna": 97, "Vitara": 98, "WR-V": 99, "Wagon R": 100, "Wrangler": 101, "X-Trail": 102, "X1": 103, "X3": 104, "X4": 105, "X5": 106, "XC": 107, "XC60": 108, "XC90": 109, "XE": 110, "XF": 111, "XL6": 112, "XUV300": 113, "XUV500": 114, "Yaris": 115, "Z4": 116, "i10": 117, "i20": 118, "redi-GO": 119}